{
  "saved_time": "20260307-161047",
  "run_dir": "D:\\Materials\\Master\\Dissertation\\Final\\Code\\MIGO\\FilterDesign-MIGO\\ber_coeff_workspace\\result\\method-wls-n-161-q-bit-8-wp-pi-0-047-width-pi-0-031",
  "cfg": {
    "N": 161,
    "mode": "lowpass",
    "wp_pi": 0.046875,
    "width_pi": 0.03125,
    "omega_1": 0.14726215563702155,
    "omega_2": 0.2454369260617026,
    "K": 256,
    "debug": true,
    "Q_bit": 8,
    "Delta": 0.00390625,
    "K_q": 127,
    "method": "WLS",
    "keys": "method N Q_bit wp_pi width_pi",
    "weight_pass": 1.0,
    "weight_stop": 100.0,
    "n_grid": 8192,
    "p": 16.0,
    "max_iters": 30,
    "tol": 0.0001,
    "eps_w": 1e-6,
    "w_clip": 1000000.0,
    "ridge": 1e-12,
    "lb_drop": 10,
    "rounding_var": 650
  },
  "solved_var": {
    "hq": [
      0.0,
      0.0,
      0.0,
      0.0,
      0.0,
      0.0,
      0.0,
      0.0,
      0.0,
      0.0,
      0.0,
      0.0,
      0.0,
      0.0,
      0.0,
      0.0,
      0.0,
      0.0,
      0.0,
      0.0,
      0.0,
      0.0,
      -0.00390625,
      -0.00390625,
      -0.00390625,
      -0.00390625,
      -0.00390625,
      -0.00390625,
      0.0,
      0.0,
      0.0,
      0.0,
      0.0,
      0.0,
      0.0,
      0.00390625,
      0.00390625,
      0.00390625,
      0.00390625,
      0.00390625,
      0.00390625,
      0.00390625,
      0.00390625,
      0.00390625,
      0.00390625,
      0.00390625,
      0.00390625,
      0.0,
      0.0,
      0.0,
      -0.00390625,
      -0.00390625,
      -0.0078125,
      -0.0078125,
      -0.0078125,
      -0.01171875,
      -0.01171875,
      -0.01171875,
      -0.01171875,
      -0.01171875,
      -0.01171875,
      -0.0078125,
      -0.00390625,
      -0.00390625,
      0.0,
      0.00390625,
      0.0078125,
      0.01171875,
      0.01953125,
      0.0234375,
      0.02734375,
      0.03515625,
      0.0390625,
      0.04296875,
      0.046875,
      0.05078125,
      0.0546875,
      0.05859375,
      0.05859375,
      0.0625,
      0.0625,
      0.0625,
      0.05859375,
      0.05859375,
      0.0546875,
      0.05078125,
      0.046875,
      0.04296875,
      0.0390625,
      0.03515625,
      0.02734375,
      0.0234375,
      0.01953125,
      0.01171875,
      0.0078125,
      0.00390625,
      0.0,
      -0.00390625,
      -0.00390625,
      -0.0078125,
      -0.01171875,
      -0.01171875,
      -0.01171875,
      -0.01171875,
      -0.01171875,
      -0.01171875,
      -0.0078125,
      -0.0078125,
      -0.0078125,
      -0.00390625,
      -0.00390625,
      0.0,
      0.0,
      0.0,
      0.00390625,
      0.00390625,
      0.00390625,
      0.00390625,
      0.00390625,
      0.00390625,
      0.00390625,
      0.00390625,
      0.00390625,
      0.00390625,
      0.00390625,
      0.00390625,
      0.0,
      0.0,
      0.0,
      0.0,
      0.0,
      0.0,
      0.0,
      -0.00390625,
      -0.00390625,
      -0.00390625,
      -0.00390625,
      -0.00390625,
      -0.00390625,
      0.0,
      0.0,
      0.0,
      0.0,
      0.0,
      0.0,
      0.0,
      0.0,
      0.0,
      0.0,
      0.0,
      0.0,
      0.0,
      0.0,
      0.0,
      0.0,
      0.0,
      0.0,
      0.0,
      0.0,
      0.0,
      0.0
    ],
    "h_int": [
      0,
      0,
      0,
      0,
      0,
      0,
      0,
      0,
      0,
      0,
      0,
      0,
      0,
      0,
      0,
      0,
      0,
      0,
      0,
      0,
      0,
      0,
      -1,
      -1,
      -1,
      -1,
      -1,
      -1,
      0,
      0,
      0,
      0,
      0,
      0,
      0,
      1,
      1,
      1,
      1,
      1,
      1,
      1,
      1,
      1,
      1,
      1,
      1,
      0,
      0,
      0,
      -1,
      -1,
      -2,
      -2,
      -2,
      -3,
      -3,
      -3,
      -3,
      -3,
      -3,
      -2,
      -1,
      -1,
      0,
      1,
      2,
      3,
      5,
      6,
      7,
      9,
      10,
      11,
      12,
      13,
      14,
      15,
      15,
      16,
      16,
      16,
      15,
      15,
      14,
      13,
      12,
      11,
      10,
      9,
      7,
      6,
      5,
      3,
      2,
      1,
      0,
      -1,
      -1,
      -2,
      -3,
      -3,
      -3,
      -3,
      -3,
      -3,
      -2,
      -2,
      -2,
      -1,
      -1,
      0,
      0,
      0,
      1,
      1,
      1,
      1,
      1,
      1,
      1,
      1,
      1,
      1,
      1,
      1,
      0,
      0,
      0,
      0,
      0,
      0,
      0,
      -1,
      -1,
      -1,
      -1,
      -1,
      -1,
      0,
      0,
      0,
      0,
      0,
      0,
      0,
      0,
      0,
      0,
      0,
      0,
      0,
      0,
      0,
      0,
      0,
      0,
      0,
      0,
      0,
      0
    ],
    "h_length": 161,
    "h": [
      0.00011092672656524852,
      0.00020371892460282364,
      0.0003061223029216414,
      0.00041490304854863624,
      0.0005242357378233644,
      0.0006290121300278856,
      0.0007219045069314142,
      0.0007968036301072422,
      0.0008459970043971513,
      0.000863699942922029,
      0.0008432980809092409,
      0.0007809077405112245,
      0.0006726080395175186,
      0.0005179480784268295,
      0.00031708200175414956,
      0.00007413634345716758,
      -0.00020583419556088087,
      -0.000513692503739859,
      -0.0008395024240483821,
      -0.0011696299995813206,
      -0.0014902874090209615,
      -0.001784887472729255,
      -0.0020378205530837325,
      -0.0022320087413994294,
      -0.0023528367935804822,
      -0.0023858036103020547,
      -0.0023204845082037684,
      -0.0021481413061192525,
      -0.0018655666250985917,
      -0.001472498872527965,
      -0.0009751972857010647,
      -0.0003835200965744751,
      0.0002858946797875811,
      0.0010129893558184716,
      0.0017715717871958092,
      0.0025331506158786537,
      0.0032646845389582143,
      0.003932849522875515,
      0.004502167053620349,
      0.004939577459799162,
      0.005212783472822813,
      0.005294932980594633,
      0.005162954710541176,
      0.004802108705319525,
      0.0042040630940069065,
      0.0033710619852895226,
      0.002313504270155914,
      0.0010535116673762398,
      -0.00037817580039463763,
      -0.0019393758245249098,
      -0.0035803468099550374,
      -0.005241747815329526,
      -0.0068592804034137405,
      -0.00836235148524664,
      -0.009679332147313141,
      -0.010736723718696127,
      -0.011464781606535104,
      -0.011796888172762823,
      -0.011675210634685471,
      -0.011049926921097944,
      -0.00988455386338894,
      -0.008154666061008098,
      -0.00585255221279828,
      -0.002985116378034858,
      0.0004224037763550004,
      0.004329563707411011,
      0.008678076840524898,
      0.013396041705186887,
      0.018396385139989205,
      0.023582106317338165,
      0.028845637393319523,
      0.0340748705123698,
      0.03915313630547108,
      0.04396565854916107,
      0.04839975171129275,
      0.052351275082773784,
      0.05572460720791269,
      0.05843865945545189,
      0.060426205623840545,
      0.06163906720652659,
      0.062046458860247955,
      0.06163906720652659,
      0.060426205623840545,
      0.05843865945545189,
      0.05572460720791269,
      0.052351275082773784,
      0.04839975171129275,
      0.04396565854916107,
      0.03915313630547108,
      0.0340748705123698,
      0.028845637393319523,
      0.023582106317338165,
      0.018396385139989205,
      0.013396041705186887,
      0.008678076840524898,
      0.004329563707411011,
      0.0004224037763550004,
      -0.002985116378034858,
      -0.00585255221279828,
      -0.008154666061008098,
      -0.00988455386338894,
      -0.011049926921097944,
      -0.011675210634685471,
      -0.011796888172762823,
      -0.011464781606535104,
      -0.010736723718696127,
      -0.009679332147313141,
      -0.00836235148524664,
      -0.0068592804034137405,
      -0.005241747815329526,
      -0.0035803468099550374,
      -0.0019393758245249098,
      -0.00037817580039463763,
      0.0010535116673762398,
      0.002313504270155914,
      0.0033710619852895226,
      0.0042040630940069065,
      0.004802108705319525,
      0.005162954710541176,
      0.005294932980594633,
      0.005212783472822813,
      0.004939577459799162,
      0.004502167053620349,
      0.003932849522875515,
      0.0032646845389582143,
      0.0025331506158786537,
      0.0017715717871958092,
      0.0010129893558184716,
      0.0002858946797875811,
      -0.0003835200965744751,
      -0.0009751972857010647,
      -0.001472498872527965,
      -0.0018655666250985917,
      -0.0021481413061192525,
      -0.0023204845082037684,
      -0.0023858036103020547,
      -0.0023528367935804822,
      -0.0022320087413994294,
      -0.0020378205530837325,
      -0.001784887472729255,
      -0.0014902874090209615,
      -0.0011696299995813206,
      -0.0008395024240483821,
      -0.000513692503739859,
      -0.00020583419556088087,
      0.00007413634345716758,
      0.00031708200175414956,
      0.0005179480784268295,
      0.0006726080395175186,
      0.0007809077405112245,
      0.0008432980809092409,
      0.000863699942922029,
      0.0008459970043971513,
      0.0007968036301072422,
      0.0007219045069314142,
      0.0006290121300278856,
      0.0005242357378233644,
      0.00041490304854863624,
      0.0003061223029216414,
      0.00020371892460282364,
      0.00011092672656524852
    ]
  },
  "solved_param": {
    "omega_grid": [
      0.0,
      0.013387468694274686,
      0.026774937388549372,
      0.04016240608282406,
      0.053549874777098744,
      0.06693734347137342,
      0.08032481216564812,
      0.09371228085992281,
      0.10709974955419749,
      0.12048721824847217,
      0.13387468694274685,
      0.14726215563702155,
      0.2454369260617026,
      0.2574045117126451,
      0.26937209736358764,
      0.28133968301453016,
      0.2933072686654727,
      0.3052748543164152,
      0.31724243996735774,
      0.32921002561830026,
      0.3411776112692428,
      0.3531451969201853,
      0.36511278257112784,
      0.37708036822207036,
      0.38904795387301283,
      0.4010155395239554,
      0.4129831251748979,
      0.42495071082584046,
      0.43691829647678293,
      0.4488858821277255,
      0.460853467778668,
      0.47282105342961056,
      0.48478863908055303,
      0.49675622473149555,
      0.5087238103824381,
      0.5206913960333805,
      0.5326589816843231,
      0.5446265673352657,
      0.5565941529862082,
      0.5685617386371506,
      0.5805293242880932,
      0.5924969099390358,
      0.6044644955899783,
      0.6164320812409207,
      0.6283996668918633,
      0.6403672525428059,
      0.6523348381937484,
      0.6643024238446908,
      0.6762700094956334,
      0.688237595146576,
      0.7002051807975185,
      0.712172766448461,
      0.7241403520994035,
      0.7361079377503461,
      0.7480755234012886,
      0.760043109052231,
      0.7720106947031735,
      0.7839782803541162,
      0.7959458660050587,
      0.8079134516560011,
      0.8198810373069436,
      0.8318486229578863,
      0.8438162086088288,
      0.8557837942597712,
      0.8677513799107137,
      0.8797189655616564,
      0.8916865512125989,
      0.9036541368635413,
      0.9156217225144838,
      0.9275893081654265,
      0.939556893816369,
      0.9515244794673114,
      0.9634920651182539,
      0.9754596507691966,
      0.9874272364201391,
      0.9993948220710815,
      1.011362407722024,
      1.0233299933729665,
      1.0352975790239092,
      1.0472651646748516,
      1.0592327503257941,
      1.0712003359767366,
      1.0831679216276793,
      1.0951355072786217,
      1.1071030929295642,
      1.1190706785805067,
      1.1310382642314494,
      1.1430058498823918,
      1.1549734355333343,
      1.1669410211842768,
      1.1789086068352195,
      1.190876192486162,
      1.2028437781371044,
      1.2148113637880469,
      1.2267789494389896,
      1.238746535089932,
      1.2507141207408745,
      1.2626817063918172,
      1.2746492920427597,
      1.2866168776937021,
      1.2985844633446446,
      1.3105520489955873,
      1.3225196346465298,
      1.3344872202974722,
      1.3464548059484147,
      1.3584223915993574,
      1.3703899772502999,
      1.3823575629012423,
      1.3943251485521848,
      1.4062927342031273,
      1.41826031985407,
      1.4302279055050124,
      1.442195491155955,
      1.4541630768068974,
      1.46613066245784,
      1.4780982481087825,
      1.490065833759725,
      1.5020334194106675,
      1.5140010050616102,
      1.5259685907125526,
      1.537936176363495,
      1.5499037620144376,
      1.5618713476653803,
      1.5738389333163227,
      1.5858065189672652,
      1.5977741046182077,
      1.6097416902691504,
      1.6217092759200928,
      1.6336768615710353,
      1.6456444472219778,
      1.6576120328729205,
      1.669579618523863,
      1.6815472041748054,
      1.6935147898257479,
      1.7054823754766906,
      1.717449961127633,
      1.7294175467785755,
      1.741385132429518,
      1.7533527180804607,
      1.7653203037314031,
      1.7772878893823456,
      1.789255475033288,
      1.8012230606842305,
      1.8131906463351732,
      1.8251582319861157,
      1.8371258176370582,
      1.8490934032880006,
      1.8610609889389433,
      1.8730285745898858,
      1.8849961602408283,
      1.8969637458917707,
      1.9089313315427134,
      1.920898917193656,
      1.9328665028445984,
      1.9448340884955408,
      1.9568016741464835,
      1.968769259797426,
      1.9807368454483685,
      1.992704431099311,
      2.0046720167502534,
      2.016639602401196,
      2.0286071880521384,
      2.040574773703081,
      2.0525423593540237,
      2.064509945004966,
      2.0764775306559087,
      2.088445116306851,
      2.1004127019577936,
      2.1123802876087363,
      2.1243478732596786,
      2.1363154589106212,
      2.148283044561564,
      2.160250630212506,
      2.172218215863449,
      2.184185801514391,
      2.196153387165334,
      2.2081209728162765,
      2.2200885584672188,
      2.2320561441181614,
      2.2440237297691037,
      2.2559913154200464,
      2.267958901070989,
      2.2799264867219318,
      2.291894072372874,
      2.3038616580238167,
      2.315829243674759,
      2.3277968293257016,
      2.3397644149766443,
      2.3517320006275866,
      2.3636995862785293,
      2.375667171929472,
      2.387634757580414,
      2.399602343231357,
      2.411569928882299,
      2.423537514533242,
      2.4355051001841845,
      2.447472685835127,
      2.4594402714860695,
      2.471407857137012,
      2.4833754427879544,
      2.495343028438897,
      2.5073106140898394,
      2.519278199740782,
      2.5312457853917247,
      2.543213371042667,
      2.5551809566936097,
      2.567148542344552,
      2.5791161279954946,
      2.5910837136464373,
      2.6030512992973796,
      2.6150188849483222,
      2.626986470599265,
      2.638954056250207,
      2.65092164190115,
      2.662889227552092,
      2.674856813203035,
      2.6868243988539775,
      2.6987919845049197,
      2.7107595701558624,
      2.722727155806805,
      2.7346947414577474,
      2.74666232710869,
      2.7586299127596323,
      2.770597498410575,
      2.7825650840615177,
      2.79453266971246,
      2.8065002553634026,
      2.8184678410143453,
      2.8304354266652876,
      2.8424030123162303,
      2.8543705979671725,
      2.866338183618115,
      2.878305769269058,
      2.89027335492,
      2.902240940570943,
      2.9142085262218855,
      2.926176111872828,
      2.9381436975237705,
      2.9501112831747127,
      2.9620788688256554,
      2.974046454476598,
      2.9860140401275403,
      2.997981625778483,
      3.0099492114294253,
      3.021916797080368,
      3.0338843827313107,
      3.045851968382253,
      3.0578195540331956,
      3.0697871396841383,
      3.0817547253350805,
      3.0937223109860232,
      3.1056898966369655,
      3.117657482287908,
      3.129625067938851,
      3.141592653589793
    ],
    "weights_used": [
      1.0,
      1.0,
      1.0,
      1.0,
      1.0,
      1.0,
      1.0,
      1.0,
      1.0,
      1.0,
      1.0,
      1.0,
      1.0,
      1.0,
      1.0,
      1.0,
      1.0,
      1.0,
      1.0,
      1.0,
      1.0,
      1.0,
      1.0,
      1.0,
      1.0,
      1.0,
      1.0,
      1.0,
      1.0,
      1.0,
      1.0,
      1.0,
      1.0,
      1.0,
      1.0,
      1.0,
      1.0,
      1.0,
      1.0,
      1.0,
      1.0,
      1.0,
      1.0,
      1.0,
      1.0,
      1.0,
      1.0,
      1.0,
      1.0,
      1.0,
      1.0,
      1.0,
      1.0,
      1.0,
      1.0,
      1.0,
      1.0,
      1.0,
      1.0,
      1.0,
      1.0,
      1.0,
      1.0,
      1.0,
      1.0,
      1.0,
      1.0,
      1.0,
      1.0,
      1.0,
      1.0,
      1.0,
      1.0,
      1.0,
      1.0,
      1.0,
      1.0,
      1.0,
      1.0,
      1.0,
      1.0,
      1.0,
      1.0,
      1.0,
      1.0,
      1.0,
      1.0,
      1.0,
      1.0,
      1.0,
      1.0,
      1.0,
      1.0,
      1.0,
      1.0,
      1.0,
      1.0,
      1.0,
      1.0,
      1.0,
      1.0,
      1.0,
      1.0,
      1.0,
      1.0,
      1.0,
      1.0,
      1.0,
      1.0,
      1.0,
      1.0,
      1.0,
      1.0,
      1.0,
      1.0,
      1.0,
      1.0,
      1.0,
      1.0,
      1.0,
      1.0,
      1.0,
      1.0,
      1.0,
      1.0,
      1.0,
      1.0,
      1.0,
      1.0,
      1.0,
      1.0,
      1.0,
      1.0,
      1.0,
      1.0,
      1.0,
      1.0,
      1.0,
      1.0,
      1.0,
      1.0,
      1.0,
      1.0,
      1.0,
      1.0,
      1.0,
      1.0,
      1.0,
      1.0,
      1.0,
      1.0,
      1.0,
      1.0,
      1.0,
      1.0,
      1.0,
      1.0,
      1.0,
      1.0,
      1.0,
      1.0,
      1.0,
      1.0,
      1.0,
      1.0,
      1.0,
      1.0,
      1.0,
      1.0,
      1.0,
      1.0,
      1.0,
      1.0,
      1.0,
      1.0,
      1.0,
      1.0,
      1.0,
      1.0,
      1.0,
      1.0,
      1.0,
      1.0,
      1.0,
      1.0,
      1.0,
      1.0,
      1.0,
      1.0,
      1.0,
      1.0,
      1.0,
      1.0,
      1.0,
      1.0,
      1.0,
      1.0,
      1.0,
      1.0,
      1.0,
      1.0,
      1.0,
      1.0,
      1.0,
      1.0,
      1.0,
      1.0,
      1.0,
      1.0,
      1.0,
      1.0,
      1.0,
      1.0,
      1.0,
      1.0,
      1.0,
      1.0,
      1.0,
      1.0,
      1.0,
      1.0,
      1.0,
      1.0,
      1.0,
      1.0,
      1.0,
      1.0,
      1.0,
      1.0,
      1.0,
      1.0,
      1.0,
      1.0,
      1.0,
      1.0,
      1.0,
      1.0,
      1.0,
      1.0,
      1.0,
      1.0,
      1.0,
      1.0,
      1.0,
      1.0,
      1.0,
      1.0,
      1.0,
      1.0,
      1.0,
      1.0,
      1.0,
      1.0,
      1.0,
      1.0
    ],
    "M": 80,
    "design_matrix_shape": [
      255,
      81
    ]
  },
  "solved_info": {
    "solver_time": 0.30892324447631836,
    "residual_energy": 0.00025690200625946337,
    "matrix_rank": 81
  },
  "optimized_filter_png": "D:\\Materials\\Master\\Dissertation\\Final\\Code\\MIGO\\FilterDesign-MIGO\\ber_coeff_workspace\\result\\method-wls-n-161-q-bit-8-wp-pi-0-047-width-pi-0-031\\optimized_filter.png"
}